streamlit_globalrefresh/__init__.py
streamlit_globalrefresh/frontend/build/asset-manifest.json
streamlit_globalrefresh/frontend/build/index.html
streamlit_globalrefresh/frontend/build/static/js/main.23d4a906.js
streamlit_globalrefresh/frontend/build/static/js/main.23d4a906.js.LICENSE.txt
streamlit_globalrefresh/frontend/build/static/js/main.23d4a906.js.map
streamlit_globalrefresh-1.2.0.dist-info/LICENSE
streamlit_globalrefresh-1.2.0.dist-info/METADATA
streamlit_globalrefresh-1.2.0.dist-info/WHEEL
streamlit_globalrefresh-1.2.0.dist-info/top_level.txt
streamlit_globalrefresh-1.2.0.dist-info/RECORD
