Metadata-Version: 2.1
Name: streamlit-globalrefresh
Version: 1.2.0
Summary: Global refresh with locks for streamlit
Home-page: https://github.com/piyushK52/streamlit_globalrefresh
Author: Piyush Kumar
Author-email: piyush.kumar.iaf@gmail.com
Requires-Python: >=3.6
License-File: LICENSE
Requires-Dist: streamlit >=0.75
